LICENSE
README.md
setup.cfg
setup.py
fxpmath/__init__.py
fxpmath/callbacks.py
fxpmath/functions.py
fxpmath/objects.py
fxpmath/temp.py
fxpmath/utils.py
fxpmath.egg-info/PKG-INFO
fxpmath.egg-info/SOURCES.txt
fxpmath.egg-info/dependency_links.txt
fxpmath.egg-info/requires.txt
fxpmath.egg-info/top_level.txt