Metadata-Version: 2.1
Name: fxpmath
Version: 0.4.6
Summary: A python library for fractional fixed-point (base 2) arithmetic and binary manipulation with Numpy compatibility.
Home-page: https://github.com/francof2a/fxpmath
Author: francof2a
Author-email: empty@empty.com
License: MIT
Download-URL: https://github.com/francof2a/fxpmath/archive/0.4.6.tar.gz
Keywords: fixed point,fractional,math,python,fxpmath,fxp,arithmetic,FPGA,DSP
Platform: UNKNOWN
Classifier: Development Status :: 4 - Beta
Classifier: Programming Language :: Python :: 3
Classifier: License :: OSI Approved :: MIT License
Classifier: Operating System :: OS Independent
Classifier: Intended Audience :: Science/Research
Classifier: Topic :: Scientific/Engineering
Classifier: Topic :: Scientific/Engineering :: Mathematics
Classifier: Topic :: Scientific/Engineering :: Physics
License-File: LICENSE
